LICENSE.txt
MANIFEST.in
README.md
setup.cfg
setup.py
dippykit/__init__.py
dippykit/_utils.py
dippykit/adjustments.py
dippykit/coding.py
dippykit/image_io.py
dippykit/metrics.py
dippykit/sampling.py
dippykit/transforms.py
dippykit/utilities.py
dippykit/visualization.py
dippykit/windows.py
dippykit.egg-info/PKG-INFO
dippykit.egg-info/SOURCES.txt
dippykit.egg-info/dependency_links.txt
dippykit.egg-info/requires.txt
dippykit.egg-info/top_level.txt