Metadata-Version: 2.1
Name: dippykit
Version: 2.0.3
Summary: A Python Package for Digital Image Processing Education
Home-page: https://github.com/dippykit/dippykit
Author: Brighton Ancelin
Author-email: bancelin3@gatech.edu
License: UNKNOWN
Platform: UNKNOWN
Classifier: Development Status :: 3 - Alpha
Classifier: Intended Audience :: Education
Classifier: Programming Language :: Python :: 3
Classifier: License :: OSI Approved :: GNU General Public License v3 (GPLv3)
Classifier: Natural Language :: English
Requires-Python: >=3.5.2
